{
  "entries": [
    {
      "taskId": "4",
      "timestamp": "2025-11-08T14:43:57.491Z",
      "summary": "Created comprehensive test suite for Navbar component with 3 tests covering authentication gating, nav rendering, and active route highlighting",
      "filesModified": [
        "frontend/src/components/navigation/navbar.tsx"
      ],
      "filesCreated": [
        "frontend/src/components/navigation/navbar.test.tsx"
      ],
      "statistics": {
        "linesAdded": 138,
        "linesRemoved": 1,
        "filesChanged": 2
      },
      "artifacts": {
        "functions": [
          {
            "name": "returns null when not authenticated",
            "purpose": "Verifies Navbar component returns null when user is not authenticated",
            "location": "frontend/src/components/navigation/navbar.test.tsx:89",
            "signature": "it('returns null when not authenticated', () => {...})",
            "isExported": false
          },
          {
            "name": "renders desktop nav when authenticated",
            "purpose": "Verifies Navbar component renders navigation items when user is authenticated",
            "location": "frontend/src/components/navigation/navbar.test.tsx:100",
            "signature": "it('renders desktop nav when authenticated', () => {...})",
            "isExported": false
          },
          {
            "name": "highlights active route",
            "purpose": "Verifies Navbar component applies bg-accent class to active route based on pathname",
            "location": "frontend/src/components/navigation/navbar.test.tsx:119",
            "signature": "it('highlights active route', () => {...})",
            "isExported": false
          }
        ]
      },
      "id": "91fbc00b-607f-4413-b403-c2250bb74235"
    },
    {
      "taskId": "3",
      "timestamp": "2025-11-08T14:41:53.433Z",
      "summary": "Integrated Navbar component into app layout header between AppTitle and AuthHeader",
      "filesModified": [
        "frontend/src/app/layout.tsx"
      ],
      "filesCreated": [],
      "statistics": {
        "linesAdded": 2,
        "linesRemoved": 1,
        "filesChanged": 1
      },
      "artifacts": {
        "integrations": [
          {
            "description": "Navbar component integrated into root layout header, positioned between AppTitle and AuthHeader in flex container",
            "frontendComponent": "Navbar",
            "backendEndpoint": "N/A (client-side only)",
            "dataFlow": "Layout renders → AuthProvider provides auth context → Navbar consumes useAuth() → Shows/hides based on authentication state → User clicks nav link → Next.js client-side navigation"
          }
        ]
      },
      "id": "c01f250f-e46d-486e-8465-97edb99e75c3"
    },
    {
      "taskId": "2",
      "timestamp": "2025-11-08T14:39:34.676Z",
      "summary": "Created Navbar component with desktop horizontal navigation and mobile Sheet menu, featuring active route highlighting and authentication-based visibility",
      "filesModified": [],
      "filesCreated": [
        "frontend/src/components/navigation/navbar.tsx",
        "frontend/src/components/navigation/index.ts"
      ],
      "statistics": {
        "linesAdded": 75,
        "linesRemoved": 0,
        "filesChanged": 2
      },
      "artifacts": {
        "components": [
          {
            "name": "Navbar",
            "type": "React",
            "purpose": "Main navigation component for authenticated users with responsive desktop/mobile views and active route highlighting",
            "location": "frontend/src/components/navigation/navbar.tsx",
            "props": "None (uses React hooks: useAuth, usePathname, useState)",
            "exports": [
              "Navbar (named export via barrel export from index.ts)"
            ]
          }
        ]
      },
      "id": "cfb81a6b-1194-43d2-9245-f563ac63afd2"
    },
    {
      "taskId": "1",
      "timestamp": "2025-11-08T13:25:35.595Z",
      "summary": "Installed shadcn Sheet component for mobile navigation menu",
      "filesModified": [],
      "filesCreated": [
        "frontend/src/components/ui/sheet.tsx"
      ],
      "statistics": {
        "linesAdded": 140,
        "linesRemoved": 0,
        "filesChanged": 1
      },
      "artifacts": {
        "components": [
          {
            "name": "Sheet",
            "type": "React",
            "purpose": "Slide-out panel component built on Radix UI Dialog primitive for mobile navigation menus",
            "location": "frontend/src/components/ui/sheet.tsx",
            "props": "React.ComponentProps<typeof SheetPrimitive.Root>",
            "exports": [
              "Sheet",
              "SheetTrigger",
              "SheetClose",
              "SheetContent",
              "SheetHeader",
              "SheetFooter",
              "SheetTitle",
              "SheetDescription"
            ]
          }
        ]
      },
      "id": "0da3ae12-3359-43fd-9f41-6a80714d9d14"
    }
  ],
  "lastUpdated": "2025-11-08T14:43:57.491Z"
}